utils_www/WWW.py
utils_www/__init__.py
utils_www_nuuuwan-1.3.2.dist-info/licenses/LICENSE
utils_www_nuuuwan-1.3.2.dist-info/METADATA
utils_www_nuuuwan-1.3.2.dist-info/WHEEL
utils_www_nuuuwan-1.3.2.dist-info/top_level.txt
utils_www_nuuuwan-1.3.2.dist-info/RECORD
