Metadata-Version: 2.4
Name: utils_www-nuuuwan
Version: 1.3.2
Summary: Utilities for accessing webpages
Home-page: https://github.com/nuuuwan/utils_www
Author: Nuwan I. Senaratna
Author-email: nuuuwan@gmail.com
Project-URL: Bug Tracker, https://github.com/nuuuwan/utils_www/issues
Classifier: Programming Language :: Python :: 3
Classifier: License :: OSI Approved :: MIT License
Classifier: Operating System :: OS Independent
Requires-Python: >=3.10
License-File: LICENSE
Requires-Dist: bs4
Requires-Dist: requests
Requires-Dist: selenium
Requires-Dist: utils_base-nuuuwan
Dynamic: author
Dynamic: author-email
Dynamic: classifier
Dynamic: description-content-type
Dynamic: home-page
Dynamic: license-file
Dynamic: project-url
Dynamic: requires-dist
Dynamic: requires-python
Dynamic: summary
